red_star/__init__.py
red_star/__main__.py
red_star/channel_manager.py
red_star/client.py
red_star/command_dispatcher.py
red_star/config_manager.py
red_star/plugin_manager.py
red_star/rs_errors.py
red_star/rs_utils.py
red_star/rs_version.py
red_star/plugins/__init__.py
red_star/plugins/admin_commands.py
red_star/plugins/announcer.py
red_star/plugins/bot_management.py
red_star/plugins/channel_dump.py
red_star/plugins/channel_manager_commands.py
red_star/plugins/channel_print.py
red_star/plugins/command_permission_commands.py
red_star/plugins/custom_commands.py
red_star/plugins/diceroll.py
red_star/plugins/info.py
red_star/plugins/levelling.py
red_star/plugins/logger.py
red_star/plugins/motd.py
red_star/plugins/music_player.py
red_star/plugins/reminder.py
red_star/plugins/role_request.py
red_star/plugins/roleplay.py
red_star/plugins/roles.py
red_star/plugins/rpn_executor.py
red_star/plugins/rs_lisp.py
red_star/plugins/voting.py
red_star-3.0.2.dist-info/LICENSE
red_star-3.0.2.dist-info/METADATA
red_star-3.0.2.dist-info/WHEEL
red_star-3.0.2.dist-info/entry_points.txt
red_star-3.0.2.dist-info/top_level.txt
red_star-3.0.2.dist-info/RECORD
