Metadata-Version: 2.1
Name: red-star
Version: 3.0.2
Summary: Red Star - A general-purpose Discord bot with bonus shouting.
Home-page: https://github.com/medeor413/Red_Star
Author: medeor413
Author-email: me@medeor.me
License: MIT
Platform: any
Classifier: Development Status :: 4 - Beta
Classifier: Environment :: Console
Classifier: Framework :: AsyncIO
Classifier: Intended Audience :: Developers
Classifier: Intended Audience :: End Users/Desktop
Classifier: License :: OSI Approved :: MIT License
Classifier: Natural Language :: English
Classifier: Operating System :: OS Independent
Classifier: Programming Language :: Python :: 3.10
Classifier: Topic :: Communications :: Chat
Requires-Python: ~=3.10
License-File: LICENSE
Requires-Dist: discord.py[voice] (<3.0.0,>=2.1.1)
Requires-Dist: yt-dlp (>=2023.02.17)
Requires-Dist: setuptools
